soops/__init__.py
soops/base.py
soops/cliargs.py
soops/find_studies.py
soops/formatting.py
soops/ioutils.py
soops/parsing.py
soops/plot_selected.py
soops/plugins.py
soops/print_info.py
soops/run_parametric.py
soops/scoop_outputs.py
soops/show_jobs.py
soops/timing.py
soops/version.py
soops/examples/__init__.py
soops/examples/monty_hall.py
soops/tests/test_scripts.py
soops-2025.2.dist-info/licenses/LICENSE.txt
soops-2025.2.dist-info/METADATA
soops-2025.2.dist-info/WHEEL
soops-2025.2.dist-info/entry_points.txt
soops-2025.2.dist-info/top_level.txt
soops-2025.2.dist-info/RECORD
