Metadata-Version: 2.4
Name: soops
Version: 2025.2
Summary: Run parametric studies and scoop output files.
Home-page: https://github.com/rc/soops
Author: Robert Cimrman
Author-email: cimrman3@ntc.zcu.cz
License: BSD
Keywords: run parametric studies,scoop output
Classifier: Development Status :: 3 - Alpha
Classifier: License :: OSI Approved :: BSD License
Classifier: Operating System :: OS Independent
Classifier: Programming Language :: Python :: 3
Classifier: Topic :: Scientific/Engineering
Classifier: Topic :: Utilities
Requires-Python: >=3.6
License-File: LICENSE.txt
Requires-Dist: pyparsing
Requires-Dist: dask
Requires-Dist: distributed
Requires-Dist: pandas
Requires-Dist: tables
Requires-Dist: matplotlib
Dynamic: license-file
